goespy/Downloader.py
goespy/__init__.py
goespy/checkData.py
goespy/goesteste.py
goespy/utils.py
goespy-0.2.dist-info/DESCRIPTION.rst
goespy-0.2.dist-info/METADATA
goespy-0.2.dist-info/RECORD
goespy-0.2.dist-info/WHEEL
goespy-0.2.dist-info/metadata.json
goespy-0.2.dist-info/top_level.txt
