Metadata-Version: 2.0
Name: goespy
Version: 0.2
Summary: A Python package can be useful to download dataset from goes satellite on AWS
Home-page: https://github.com/palexandremello/goes-py
Author: Paulo Alexandre Mello
Author-email: palexandremello@gmail.com
License: BSD 2-Clause License
Keywords: weather goes satellite meteorology noaa
Platform: UNKNOWN
Requires-Dist: boto3
Requires-Dist: botocore
Requires-Dist: pathlib
